odoo10_addon_hr_employee_product-10.0.1.0.0-py2.7-nspkg.pth
odoo/addons/hr_employee_product/README.rst
odoo/addons/hr_employee_product/__init__.py
odoo/addons/hr_employee_product/__manifest__.py
odoo/addons/hr_employee_product/model/__init__.py
odoo/addons/hr_employee_product/model/product.py
odoo/addons/hr_employee_product/security/product_security.xml
odoo/addons/hr_employee_product/static/description/icon.png
odoo/addons/hr_employee_product/view/product.xml
odoo10_addon_hr_employee_product-10.0.1.0.0.dist-info/DESCRIPTION.rst
odoo10_addon_hr_employee_product-10.0.1.0.0.dist-info/METADATA
odoo10_addon_hr_employee_product-10.0.1.0.0.dist-info/RECORD
odoo10_addon_hr_employee_product-10.0.1.0.0.dist-info/WHEEL
odoo10_addon_hr_employee_product-10.0.1.0.0.dist-info/metadata.json
odoo10_addon_hr_employee_product-10.0.1.0.0.dist-info/namespace_packages.txt
odoo10_addon_hr_employee_product-10.0.1.0.0.dist-info/top_level.txt
